alei_utils/__init__.py
alei_utils/__version__.py
alei_utils/logger.py
alei_utils-0.1.3.dist-info/LICENSE
alei_utils-0.1.3.dist-info/METADATA
alei_utils-0.1.3.dist-info/WHEEL
alei_utils-0.1.3.dist-info/top_level.txt
alei_utils-0.1.3.dist-info/RECORD
